tests/__init__.py
tests/test_functional.py
tests/test_handlers.py
ubarec/__init__.py
ubarec/__main__.py
ubarec/_defaults.py
ubarec/_version.py
ubarec/backup.py
ubarec/drivers.py
ubarec/handlers.py
ubarec/main.py
ubarec/restore.py
ubarec-0.2.2.dist-info/LICENSE
ubarec-0.2.2.dist-info/METADATA
ubarec-0.2.2.dist-info/WHEEL
ubarec-0.2.2.dist-info/entry_points.txt
ubarec-0.2.2.dist-info/top_level.txt
ubarec-0.2.2.dist-info/RECORD
