Metadata-Version: 2.1
Name: ubarec
Version: 0.2.2
Summary: Universal backup and recovery using S3 repo
Home-page: http://github.com/fgbm/ubarec
Author: Chmelyuk Vladislav
Author-email: neimp@yandex.ru
License: UNKNOWN
Platform: UNKNOWN
Classifier: License :: OSI Approved :: MIT License
Classifier: Natural Language :: Russian
Classifier: Operating System :: OS Independent
Classifier: Programming Language :: Python
Classifier: Programming Language :: Python :: 3
Classifier: Programming Language :: Python :: 3 :: Only
Classifier: Programming Language :: Python :: 3.7
Classifier: Programming Language :: Python :: 3.8
Classifier: Programming Language :: Python :: 3.9
Classifier: Programming Language :: Python :: 3.10
Classifier: Topic :: System :: Archiving :: Backup
Classifier: Topic :: Utilities
Requires-Dist: typer
Requires-Dist: pyodbc
Requires-Dist: colorama
Requires-Dist: boto3
Requires-Dist: loguru
Requires-Dist: pydantic
